Workbook

Sheet Tổng quan
A1: FlowWise - Sheet tổng hợp nghiệp vụ shop Shopee / TikTok Shop
A2: Dùng để xác minh quy tắc trước khi chốt dữ liệu demo và logic tính. Ô vàng chữ xanh là ô cần điền.
A4: Tiến độ xác minh quy tắc
A5: Tổng số quy tắc | B5: =COUNTA('Quy tắc nghiệp vụ'!A6:A39)-6 -> 28
A6: Đã xác minh | B6: =COUNTIF('Quy tắc nghiệp vụ'!H6:H39,"Đã xác minh*") -> 0
A7: Chưa xác minh | B7: =COUNTIF('Quy tắc nghiệp vụ'!H6:H39,"Chưa xác minh") -> 28
A8: Mâu thuẫn cần xử lý | B8: =COUNTIF('Quy tắc nghiệp vụ'!H6:H39,"Mâu thuẫn") -> 0
A9: Tỷ lệ đã xác minh | B9: =IF(B5=0,0,B6/B5) -> 0
A10: Số seller đã phỏng vấn | B10: =COUNTA('Phỏng vấn seller'!D6:F6) -> 0
A11: Dòng settlement bị lệch (kiểm tra đối soát) | B11: ='Kiểm tra đối soát'!B37 -> 1
A13: Cách dùng
A14: 1. Quy tắc nghiệp vụ: điền giá trị cho Shopee/TikTok kèm nguồn và ngày tra cứu, chọn trạng thái.
A15: 2. Cấu trúc settlement: khi có file đối soát thật, ghi tên cột gốc ứng với từng cột schema.
A16: 3. Kiểm tra đối soát: dán các dòng settlement để phát hiện dòng cộng không ra (nguyên nhân thường là cột bị ẩn).
A17: 4. Phỏng vấn seller: ghi câu trả lời theo từng seller (ẩn danh). Các mã R.. trỏ về sheet Quy tắc để cập nhật.
A18: 5. Nguồn: ghi link và ngày tra cứu. Giá trị chưa có nguồn thì để trống, không điền theo trí nhớ.
A19: Màu: chữ xanh dương = ô nhập; chữ đen = công thức/nội dung cố định; chữ xanh lá = liên kết từ sheet khác; nền vàng = ô cần điền.

Sheet Quy tắc nghiệp vụ
A1: Quy tắc nghiệp vụ Shopee / TikTok Shop cần xác minh
A2: Ô vàng chữ xanh = ô bạn điền. Chỉ điền giá trị đã có nguồn; chưa chắc thì để trống và giữ trạng thái 'Chưa xác minh'.
A3: Dòng VD là ví dụ cách ghi (số liệu minh họa, không phải chính sách thật) – xóa khi dùng.
A4: Mã | B4: Nhóm | C4: Câu hỏi cần xác minh | D4: Shopee | E4: TikTok Shop | F4: Nguồn (link chính sách / seller nào) | G4: Ngày tra cứu | H4: Trạng thái | I4: Ảnh hưởng tới (trong FlowWise) | J4: Ghi chú
A5: VD | B5: Payout & thời điểm tiền về | C5: Từ mốc đó đến khi tiền về ví sàn mất bao nhiêu ngày (T+?) | D5: (ví dụ) T+X ngày sau mốc Y | E5: (ví dụ) T+Z ngày | F5: Trang chính sách thanh toán của sàn; Seller A | G5: 2026-10-13 | H5: VÍ DỤ | I5: expected_payout_date | J5: Ghi rõ ngày tra cứu vì chính sách có thể đổi
A6: Payout & thời điểm tiền về
A7: R01 | B7: Payout & thời điểm tiền về | C7: Chu kỳ đối soát/chi trả là gì (theo đơn, hằng ngày, hằng tuần, khác)? | H7: Chưa xác minh | I7: Tần suất của cash event
A8: R02 | B8: Payout & thời điểm tiền về | C8: Mốc bắt đầu tính ngày trả tiền (giao thành công / người mua xác nhận / hết hạn đổi trả)? | H8: Chưa xác minh | I8: Ngày của cash event
A9: R03 | B9: Payout & thời điểm tiền về | C9: Từ mốc đó đến khi tiền về ví sàn mất bao nhiêu ngày (T+?) | H9: Chưa xác minh | I9: expected_payout_date
A10: R04 | B10: Payout & thời điểm tiền về | C10: Từ ví sàn rút về ngân hàng mất bao lâu, có phí rút không? | H10: Chưa xác minh | I10: Độ trễ ví → ngân hàng
A11: R05 | B11: Payout & thời điểm tiền về | C11: Tiền bị giữ lại (escrow/hold) bao lâu, điều kiện giải phóng? | H11: Chưa xác minh | I11: reserve_or_hold + ngày release
A12: R06 | B12: Payout & thời điểm tiền về | C12: Ngày nghỉ/lễ có làm lệch ngày tiền về không? | H12: Chưa xác minh | I12: Tuần rơi của cash event
A13: Phí và các khoản trừ
A14: R07 | B14: Phí và các khoản trừ | C14: Phí hoa hồng/phí cố định: mức % theo ngành hàng đã chọn? | H14: Chưa xác minh | I14: platform_fee
A15: R08 | B15: Phí và các khoản trừ | C15: Phí giao dịch/thanh toán: mức và cách tính? | H15: Chưa xác minh | I15: platform_fee
A16: R09 | B16: Phí và các khoản trừ | C16: Các phí dịch vụ/chương trình tùy chọn người bán hay đăng ký? | H16: Chưa xác minh | I16: platform_fee
A17: R10 | B17: Phí và các khoản trừ | C17: Voucher/khuyến mãi do người bán chịu: trừ vào đâu, khi nào? | H17: Chưa xác minh | I17: platform_fee hoặc cột riêng
A18: R11 | B18: Phí và các khoản trừ | C18: Phí vận chuyển người bán chịu / chênh lệch phí ship? | H18: Chưa xác minh | I18: shipping_or_COD_fee
A19: R12 | B19: Phí và các khoản trừ | C19: Phí COD (nếu có): ai chịu, mức bao nhiêu? | H19: Chưa xác minh | I19: shipping_or_COD_fee
A20: R13 | B20: Phí và các khoản trừ | C20: Hoa hồng liên kết/affiliate/creator (nếu có): tính thế nào? | H20: Chưa xác minh | I20: Cột phí mới nếu cần
A21: Hoàn/huỷ và điều chỉnh
A22: R14 | B22: Hoàn/huỷ và điều chỉnh | C22: Đơn hoàn/huỷ: tiền hoàn trừ vào kỳ payout nào, có hoàn lại phí không? | H22: Chưa xác minh | I22: refunds
A23: R15 | B23: Hoàn/huỷ và điều chỉnh | C23: Tỷ lệ hoàn/huỷ thường gặp ở ngành hàng đã chọn? | H23: Chưa xác minh | I23: Giả định hoàn tiền trong forecast
A24: R16 | B24: Hoàn/huỷ và điều chỉnh | C24: Khiếu nại/tranh chấp: tiền bị giữ thế nào, bao lâu? | H24: Chưa xác minh | I24: reserve_or_hold
A25: R17 | B25: Hoàn/huỷ và điều chỉnh | C25: Phạt/điều chỉnh do vi phạm: có khấu trừ vào payout không? | H25: Chưa xác minh | I25: Khoản điều chỉnh
A26: Dữ liệu xuất ra (cho phần Data input)
A27: R18 | B27: Dữ liệu xuất ra (cho phần Data input) | C27: Báo cáo đối soát nào xuất được, tên báo cáo, định dạng (xlsx/csv)? | H27: Chưa xác minh | I27: Mẫu file ingestion
A28: R19 | B28: Dữ liệu xuất ra (cho phần Data input) | C28: Danh sách cột thực tế trong file đối soát (tên gốc)? | H28: Chưa xác minh | I28: Mapping cột → schema
A29: R20 | B29: Dữ liệu xuất ra (cho phần Data input) | C29: Xuất được tối đa bao nhiêu ngày/lần? | H29: Chưa xác minh | I29: Giới hạn tải dữ liệu
A30: R21 | B30: Dữ liệu xuất ra (cho phần Data input) | C30: Có mã tham chiếu để khớp với sao kê ngân hàng không? | H30: Chưa xác minh | I30: reference_id / chống tính trùng
A31: Nhập hàng và tiền tệ
A32: R22 | B32: Nhập hàng và tiền tệ | C32: Nhập hàng từ đâu là chủ yếu (1688, NCC trong nước, khác)? | H32: Chưa xác minh | I32: Có cần CNY hay không
A33: R23 | B33: Nhập hàng và tiền tệ | C33: Trả tiền nhập hàng thế nào: trả trước hay công nợ, bằng đồng tiền nào, qua kênh nào? | H33: Chưa xác minh | I33: payables.currency
A34: R24 | B34: Nhập hàng và tiền tệ | C34: Kỳ hạn trả nhà cung cấp thường gặp? | H34: Chưa xác minh | I34: payables.due_date
A35: R25 | B35: Nhập hàng và tiền tệ | C35: Có khoản chi bằng USD thường xuyên không (quảng cáo, vận chuyển quốc tế)? | H35: Chưa xác minh | I35: Có cần USD hay không
A36: Vận hành tài chính của shop
A37: R26 | B37: Vận hành tài chính của shop | C37: Shop đang theo dõi tiền bằng gì (Excel, sổ, phần mềm kế toán, không theo dõi)? | H37: Chưa xác minh | I37: Định dạng đầu vào, lý do cần FlowWise
A38: R27 | B38: Vận hành tài chính của shop | C38: Ai đối soát, mất bao lâu mỗi tuần/tháng? | H38: Chưa xác minh | I38: Giá trị tiết kiệm thời gian
A39: R28 | B39: Vận hành tài chính của shop | C39: Lần gần nhất thiếu tiền: nguyên nhân là gì? | H39: Chưa xác minh | I39: Loại cảnh báo đáng làm nhất

Sheet Cấu trúc settlement
A1: Ánh xạ cột settlement của sàn → schema FlowWise
A2: Điền tên cột thật khi có file đối soát mẫu. Cột 'Dấu' cho biết khoản cộng hay trừ vào tiền thực nhận.
A4: Cột schema FlowWise | B4: Ý nghĩa | C4: Dấu | D4: Tên cột thật - Shopee | E4: Tên cột thật - TikTok Shop | F4: Công thức / mức phí đã xác minh | G4: Trạng thái
A5: gross_sales | B5: Doanh số đủ điều kiện trong kỳ | C5: + | G5: Chưa xác minh
A6: platform_fee | B6: Phí sàn (hoa hồng, giao dịch, dịch vụ, voucher người bán chịu) | C6: - | G6: Chưa xác minh
A7: refunds | B7: Hoàn tiền / huỷ đơn | C7: - | G7: Chưa xác minh
A8: shipping_or_COD_fee | B8: Phí vận chuyển người bán chịu, phí COD | C8: - | G8: Chưa xác minh
A9: reserve_or_hold | B9: Tiền sàn giữ lại, dự kiến giải phóng sau | C9: - | G9: Chưa xác minh
A10: net_payout | B10: Tiền thực nhận trong kỳ theo báo cáo sàn | G10: Chưa xác minh
A11: expected_payout_date | B11: Ngày dự kiến tiền về | C11: - | G11: Chưa xác minh
A12: actual_payout_date | B12: Ngày tiền thật sự về (đối chiếu sao kê) | C12: - | G12: Chưa xác minh
A14: Lưu ý logic: tiền bị giữ (hold) chỉ hoãn thời điểm nhận tiền chứ không mất đi, nên cần thêm một cash event ngày giải phóng.

Sheet Kiểm tra đối soát
A1: Kiểm tra dòng settlement có cộng ra đúng không
A2: Nhập các khoản trừ dưới dạng số DƯƠNG. Net tính lại = Gross − Phí − Hoàn − Ship/COD − Hold.
A3: Dung sai (VND) | B3: 1000 | C3: Chênh lệch ≤ dung sai thì coi là khớp
A5: Ngày | B5: Gross | C5: Phí sàn | D5: Hoàn/huỷ | E5: Ship/COD | F5: Hold | G5: Net theo báo cáo sàn | H5: Net tính lại | I5: Chênh lệch | J5: Kết quả
A6: VD 2026-10-06 (thiếu cột Ship/COD) | B6: 45000000 | C6: 5400000 | D6: 0 | E6: 0 | F6: 4500000 | G6: 31500000 | H6: =IF(B6="","",B6-C6-D6-E6-F6) -> 35100000 | I6: =IF(B6="","",G6-H6) -> -3600000 | J6: =IF(B6="","",IF(ABS(I6)<=$B$3,"Khớp","LỆCH")) -> LỆCH
A7: VD 2026-10-06 (đã thêm Ship/COD) | B7: 45000000 | C7: 5400000 | D7: 0 | E7: 3600000 | F7: 4500000 | G7: 31500000 | H7: =IF(B7="","",B7-C7-D7-E7-F7) -> 31500000 | I7: =IF(B7="","",G7-H7) -> 0 | J7: =IF(B7="","",IF(ABS(I7)<=$B$3,"Khớp","LỆCH")) -> Khớp
H8: =IF(B8="","",B8-C8-D8-E8-F8) | I8: =IF(B8="","",G8-H8) | J8: =IF(B8="","",IF(ABS(I8)<=$B$3,"Khớp","LỆCH"))
H9: =IF(B9="","",B9-C9-D9-E9-F9) | I9: =IF(B9="","",G9-H9) | J9: =IF(B9="","",IF(ABS(I9)<=$B$3,"Khớp","LỆCH"))
H10: =IF(B10="","",B10-C10-D10-E10-F10) | I10: =IF(B10="","",G10-H10) | J10: =IF(B10="","",IF(ABS(I10)<=$B$3,"Khớp","LỆCH"))
H11: =IF(B11="","",B11-C11-D11-E11-F11) | I11: =IF(B11="","",G11-H11) | J11: =IF(B11="","",IF(ABS(I11)<=$B$3,"Khớp","LỆCH"))
H12: =IF(B12="","",B12-C12-D12-E12-F12) | I12: =IF(B12="","",G12-H12) | J12: =IF(B12="","",IF(ABS(I12)<=$B$3,"Khớp","LỆCH"))
H13: =IF(B13="","",B13-C13-D13-E13-F13) | I13: =IF(B13="","",G13-H13) | J13: =IF(B13="","",IF(ABS(I13)<=$B$3,"Khớp","LỆCH"))
H14: =IF(B14="","",B14-C14-D14-E14-F14) | I14: =IF(B14="","",G14-H14) | J14: =IF(B14="","",IF(ABS(I14)<=$B$3,"Khớp","LỆCH"))
H15: =IF(B15="","",B15-C15-D15-E15-F15) | I15: =IF(B15="","",G15-H15) | J15: =IF(B15="","",IF(ABS(I15)<=$B$3,"Khớp","LỆCH"))
H16: =IF(B16="","",B16-C16-D16-E16-F16) | I16: =IF(B16="","",G16-H16) | J16: =IF(B16="","",IF(ABS(I16)<=$B$3,"Khớp","LỆCH"))
H17: =IF(B17="","",B17-C17-D17-E17-F17) | I17: =IF(B17="","",G17-H17) | J17: =IF(B17="","",IF(ABS(I17)<=$B$3,"Khớp","LỆCH"))
H18: =IF(B18="","",B18-C18-D18-E18-F18) | I18: =IF(B18="","",G18-H18) | J18: =IF(B18="","",IF(ABS(I18)<=$B$3,"Khớp","LỆCH"))
H19: =IF(B19="","",B19-C19-D19-E19-F19) | I19: =IF(B19="","",G19-H19) | J19: =IF(B19="","",IF(ABS(I19)<=$B$3,"Khớp","LỆCH"))
... H35: =IF(B35="","",B35-C35-D35-E35-F35) | I35: =IF(B35="","",G35-H35) | J35: =IF(B35="","",IF(ABS(I35)<=$B$3,"Khớp","LỆCH"))
A37: Số dòng lệch: | B37: =COUNTIF(J6:J35,"LỆCH") -> 1
A38: Hai dòng VD lấy số từ màn hình ingestion hiện tại; dòng 2 thêm Ship/COD = 3.600.000 để minh họa cột bị ẩn. Xóa khi dùng dữ liệu thật.

Sheet Phỏng vấn seller
A1: Bộ câu hỏi và ghi chép phỏng vấn seller
A2: Mỗi cột Seller là một người. Ẩn danh: dùng alias (Seller 1, 2, 3). Cột C là ví dụ cách ghi.
A4: Mã | B4: Câu hỏi | C4: Ví dụ cách ghi (minh họa) | D4: Seller 1 | E4: Seller 2 | F4: Seller 3
A5: A. Hồ sơ shop
A6: Q01 | B6: Alias seller và ngày phỏng vấn | C6: Seller 1 – 2026-10-14
A7: Q02 | B7: Ngành hàng chính | C7: Thời trang nữ
A8: Q03 | B8: Bán trên những kênh nào (Shopee, TikTok Shop, khác)? | C8: Shopee + TikTok Shop
A9: Q04 | B9: Ước lượng số đơn mỗi tháng | C9: khoảng vài trăm đơn
A10: Q05 | B10: Số người làm vận hành/kế toán | C10: 2 người
A11: B. Tiền sàn trả về
A12: Q06 | B12: Tiền về sau khi giao hàng bao lâu? (R03) | C12: ghi đúng lời seller
A13: Q07 | B13: Tháng vừa rồi sàn trừ những khoản nào? (R07–R13) | C13: phí, voucher, ship…
A14: Q08 | B14: Hoàn/huỷ đơn thường chiếm bao nhiêu và trừ vào đâu? (R14–R15)
A15: Q09 | B15: Có lần nào tiền về trễ hơn dự kiến không, vì sao? (R05, R16)
A16: C. Nhập hàng và tiền tệ
A17: Q10 | B17: Nhập hàng từ đâu, trả bằng đồng tiền nào, qua kênh nào? (R21–R22)
A18: Q11 | B18: Trả trước hay công nợ, kỳ hạn bao lâu? (R23)
A19: Q12 | B19: Có chi USD thường xuyên không (quảng cáo, vận chuyển)? (R24)
A20: D. Cách theo dõi tiền
A21: Q13 | B21: Đang theo dõi tiền bằng gì? (R25) | C21: Excel / sổ / phần mềm
A22: Q14 | B22: Mất bao lâu mỗi tuần để đối soát? (R26)
A23: Q15 | B23: Lần gần nhất thiếu tiền: chuyện gì xảy ra? (R27)
A24: Q16 | B24: Muốn biết điều gì nhất về tiền 1–3 tháng tới?
A25: E. Dữ liệu và đồng ý
A26: Q17 | B26: Có đồng ý chia sẻ file đối soát đã ẩn danh không? | C26: Có / Không / Chưa chắc
A27: Q18 | B27: Cho phép trích dẫn ẩn danh trong bài thi không? | C27: Có / Không

Sheet Nguồn
A1: Nguồn cần tra cứu / đã dùng
A2: Chính sách sàn có thể thay đổi: luôn ghi ngày tra cứu và dán link thật vào cột D.
A4: Nguồn | B4: Dùng để xác minh nhóm | C4: Ngày tra cứu | D4: Link / mã tài liệu | E4: Ghi chú
A5: Trung tâm hỗ trợ / Seller Education Hub của Shopee (mục thanh toán và phí) | B5: Payout, phí, hoàn/huỷ
A6: Trung tâm hỗ trợ / Seller Academy của TikTok Shop (mục thanh toán và phí) | B6: Payout, phí, hoàn/huỷ
A7: File đối soát thật xuất từ Seller Centre (đã ẩn danh) | B7: Tên cột, mapping, dữ liệu demo
A8: Phỏng vấn seller (ghi alias) | B8: Vận hành thực tế, nhập hàng, tiền tệ
A9: Sao kê ngân hàng của seller (đã ẩn danh) | B9: Ngày tiền về thực tế, độ trễ
